[
 [
  "contract_a92eae4a.hex",
  [
   "TAC_Statement_Next",
   "blockCloner",
   "Analytics_ReachableUnderContext",
   "FormalArgs",
   "Analytics_Block_NumberOfContexts",
   "Analytics_ReachableBlocksInTAC",
   "IRFunction_Return",
   "ConstantPossibleSigHash",
   "Verbatim_MemConsStmtsLengths",
   "Analytics_Jumps",
   "preTrans",
   "IRFallthroughEdge",
   "Verbatim_compiler_info",
   "Analytics_Blocks",
   "ArrayWriteToRelativeIndex",
   "PublicFunctionArg",
   "blockCloner",
   "postTrans",
   "TAC_Stmt",
   "RevertToSignature",
   "IRFunctionCallReturn",
   "AllCALLsClassified",
   "global",
   "Analytics_NonModeledMSTORE",
   "blockCloner",
   "Verbatim_AllVsModeledMSTOREs",
   "IRFunctionEntry",
   "TAC_Block_Head",
   "MemoryStatement_ActualArgNew",
   "Analytics_ArrayCopy",
   "Analytics_FunctionCallWithReturn",
   "Analytics_Block_NumberOfContextsJump",
   "TAC_Op",
   "Verbatim_CDLAllVSStaticVSArr",
   "global",
   "Function",
   "TAC_Def",
   "LocalBlockEdge",
   "Analytics_ArrayVarHasNoElementSize",
   "Analytics_PublicFunctionArrayArg",
   "TAC_Variable_Value",
   "Analytics_PublicFunction",
   "TAC_Var",
   "TAC_Block",
   "Analytics_FunctionWithMultipleReturns",
   "TAC_Variable_BlockValue",
   "bytecode",
   "Analytics_Block_TimesInContexts",
   "TAC_Statement_InlineInfo",
   "blockCloner",
   "Analytics_NonModeledMLOAD",
   "TAC_OriginalStatement_Block",
   "Analytics_PublicFunctionArg",
   "TAC_Statement_OriginalStatement",
   "TAC_Use",
   "Analytics_FunctionCall",
   "CallToSignature",
   "GlobalEntryBlock",
   "TAC_Statement_OriginalStatementList",
   "postTrans",
   "Analytics_Functions",
   "TAC_Block_CodeChunkAccessed",
   "Analytics_LocalBlockEdge",
   "Analytics_Contexts",
   "Analytics_JUMPDESTNeverPushed",
   "ActualReturnArgs",
   "preTrans",
   "global",
   "PublicFunction",
   "revertCloner",
   "Mask_Length",
   "IRFunctionCall",
   "HighLevelFunctionName",
   "Verbatim_BlocksReachabilityMetric",
   "Analytics_ReachableBlocks",
   "TAC_Block_Gas",
   "Analytics_PublicFunctionNameResolved",
   "contract",
   "revertCloner",
   "Verbatim_AllVsModeledMLOADs",
   "Analytics_BlockIsEmpty",
   "global",
   "InFunction"
  ],
  [],
  {
   "disassemble_time": 0.025400161743164062,
   "decomp_time": 7.9449687004089355,
   "inline_time": 14.048713207244873,
   "client_time": 0.07621264457702637,
   "errors": 0,
   "client_timeouts": 0,
   "bytecode_size": 18652,
   "decompiler_config": "default",
   "Analytics_PolymorphicTargetSameCtx": 0,
   "Analytics_StructHasTwoWidths": 0,
   "Analytics_ReachableUnderContext": 2440,
   "Analytics_PrivateFunctionMatchesMetadataIncorrectArgs": 0,
   "Analytics_BlockInMultipleFunctions": 0,
   "Analytics_PolymorphicStructAlt": 0,
   "Analytics_Block_NumberOfContexts": 1015,
   "Analytics_ReachableBlocksInTAC": 886,
   "Analytics_UnreachableBlock": 0,
   "Analytics_InexactFunctionReturnArguments": 0,
   "Analytics_Jumps": 750,
   "Analytics_BlocksLocalOrNot": 0,
   "Analytics_InitiallyMissedCycleEntry": 0,
   "Analytics_JumpToManyWithoutGlobalImprecision": 0,
   "Analytics_Blocks": 1093,
   "Analytics_PolymorphicStruct": 0,
   "Analytics_BlockHasNoTACBlock": 0,
   "Analytics_LenVarHasManyVars": 0,
   "Analytics_NonModeledMSTORE": 5,
   "Analytics_PolymorphicArrayVarSameCtx": 0,
   "Analytics_ArrayHasTwoElementLengths": 0,
   "Analytics_ArrayCopy": 1,
   "Analytics_FunctionCallWithReturn": 257,
   "Analytics_PolymorphicArrayVarAlt": 0,
   "Analytics_NonModeledCALLDATALOAD": 0,
   "Analytics_JumpToMany": 0,
   "Analytics_DoubleDef": 0,
   "Analytics_Block_NumberOfContextsJump": 103,
   "Analytics_PolymorphicArrayVar": 0,
   "Analytics_PrivateFunctionMatchesMetadata": 0,
   "Analytics_JumpToManyNonPopBlock": 0,
   "Analytics_InexactFunctionArguments": 0,
   "Analytics_NextRoundCloningCandidate": 0,
   "Analytics_ArrayVarHasNoElementSize": 41,
   "Analytics_PublicFunctionArrayArg": 3,
   "Analytics_PublicFunction": 38,
   "Analytics_MissingJumpTargetSomeCtx": 0,
   "Analytics_FunctionWithMultipleReturns": 2,
   "Analytics_PolymorphicTarget": 0,
   "Analytics_InexactFunctionCallArguments": 0,
   "Analytics_MissingImplementation": 0,
   "Analytics_Block_TimesInContexts": 1015,
   "Analytics_NonModeledMLOAD": 10,
   "Analytics_PublicFunctionArg": 50,
   "Analytics_FunctionCall": 295,
   "Analytics_Functions": 99,
   "Analytics_LocalBlockEdge": 1023,
   "Analytics_Contexts": 510,
   "Analytics_MemConsStmtUsesFromDistinctPaths": 0,
   "Analytics_JUMPDESTNeverPushed": 200,
   "Analytics_PolymorphicStructSameCtx": 0,
   "Analytics_PublicFunctionStructArg": 0,
   "Analytics_MissingJumpTargetAnyCtx": 0,
   "Analytics_StmtMissingOperand": 0,
   "Analytics_PrivateFunctionMatchesMetadataIncorrectReturnArgs": 0,
   "Analytics_UnknownOperand": 0,
   "Analytics_BlockInNoFunctions": 0,
   "Analytics_ReachableBlocks": 886,
   "Analytics_PublicFunctionNameResolved": 14,
   "Analytics_BlockIsEmpty": 11,
   "Analytics_DeadBlocks": 0,
   "Verbatim_MemConsStmtsLengths": "459\t371\t371\n",
   "Verbatim_compiler_info": "solidity\t0.8.12",
   "Verbatim_AllVsModeledMSTOREs": "656\t63\t2\t65\t45\t565\t0\n",
   "Verbatim_CDLAllVSStaticVSArr": "57\t51\t6\n",
   "Verbatim_BlocksReachabilityMetric": "1015\t2440\t2.40394092\n",
   "Verbatim_AllVsModeledMLOADs": "463\t377\t54\t1\t1\t0\t0\n"
  }
 ]
]